{
    "os": "Linux-6.5.0-28-generic-x86_64-with-glibc2.35",
    "python": "3.10.12",
    "heartbeatAt": "2024-04-29T09:46:46.038830",
    "startedAt": "2024-04-29T09:46:45.228306",
    "docker": null,
    "cuda": null,
    "args": [],
    "state": "running",
    "program": "<python with no main file>",
    "codePathLocal": null,
    "git": {
        "remote": "https://github.com/Houda222/SYN-MTGAN.git",
        "commit": "b8ec378fc64544496c26534880ffa54160f12c8e"
    },
    "email": "houda.ghallab@imt-atlantique.net",
    "root": "/home/hghallab/Dvlp/GANs",
    "host": "hghallab",
    "username": "hghallab",
    "executable": "/bin/python3",
    "cpu_count": 4,
    "cpu_count_logical": 8,
    "cpu_freq": {
        "current": 3889.319375,
        "min": 400.0,
        "max": 4500.0
    },
    "cpu_freq_per_core": [
        {
            "current": 4150.835,
            "min": 400.0,
            "max": 4500.0
        },
        {
            "current": 4189.676,
            "min": 400.0,
            "max": 4500.0
        },
        {
            "current": 4099.85,
            "min": 400.0,
            "max": 4500.0
        },
        {
            "current": 4194.18,
            "min": 400.0,
            "max": 4500.0
        },
        {
            "current": 4195.462,
            "min": 400.0,
            "max": 4500.0
        },
        {
            "current": 4192.002,
            "min": 400.0,
            "max": 4500.0
        },
        {
            "current": 4099.804,
            "min": 400.0,
            "max": 4500.0
        },
        {
            "current": 1985.923,
            "min": 400.0,
            "max": 4500.0
        }
    ],
    "disk": {
        "/": {
            "total": 136.6944694519043,
            "used": 81.7701187133789
        }
    },
    "memory": {
        "total": 31.207508087158203
    }
}
